pygquery/__init__.py
pygquery/bigquery.py
PygQuery-0.0.6.dist-info/LICENSE
PygQuery-0.0.6.dist-info/METADATA
PygQuery-0.0.6.dist-info/WHEEL
PygQuery-0.0.6.dist-info/top_level.txt
PygQuery-0.0.6.dist-info/RECORD
